pyconnector/driver_utils.py
pyconnector/core/base_db_connector.py
pyconnector/core/base_google_connector.py
pyconnector/databricks/__init__.py
pyconnector/databricks/api_connector.py
pyconnector/databricks/jdbc_connector.py
pyconnector/databricks/odbc_connector.py
pyconnector/databricks/sql_connector.py
pyconnector/mysql/__init__.py
pyconnector/mysql/connector.py
pyconnector/postgres/__init__.py
pyconnector/postgres/api_connector.py
pyconnector/postgres/connector.py
pyconnector/postgres/jdbc_connector.py
pyconnector/postgres/odbc_connector.py
pyconnector/pygoogle/__init__.py
pyconnector/pygoogle/drive_connector.py
pyconnector/pygoogle/gmail_connector.py
pyconnector/sftp/__init__.py
pyconnector/sftp/basic_connector.py
pyconnector/sharepoint/__init__.py
pyconnector/sharepoint/api_connector.py
pyconnector/smtp/__init__.py
pyconnector/smtp/basic_connector.py
pyconnector-0.3.1.dist-info/licenses/LICENSE
pyconnector-0.3.1.dist-info/METADATA
pyconnector-0.3.1.dist-info/WHEEL
pyconnector-0.3.1.dist-info/top_level.txt
pyconnector-0.3.1.dist-info/RECORD
