Metadata-Version: 2.4
Name: pyconnector
Version: 0.3.1
Summary: Pluggable connectors for databases and services like Databricks, Postgres, SMTP, SFTP
Home-page: https://github.com/RVAKR/pyconnector
Author: rvakr
Author-email: rvakr <contactmail.br@gmail.com>
License: MIT
Project-URL: Homepage, https://github.com/RVAKR/pyconnector
Requires-Python: >=3.7
License-File: LICENSE
Dynamic: license-file
